COPYING
LICENSE
MANIFEST.in
README.rst
distribute_setup.py
rtd_requirements.txt
setup.py
Orange_ModelMaps.egg-info/PKG-INFO
Orange_ModelMaps.egg-info/SOURCES.txt
Orange_ModelMaps.egg-info/dependency_links.txt
Orange_ModelMaps.egg-info/entry_points.txt
Orange_ModelMaps.egg-info/not-zip-safe
Orange_ModelMaps.egg-info/requires.txt
Orange_ModelMaps.egg-info/top_level.txt
docs/Makefile
docs/rst/Orange.modelmaps.model.rst
docs/rst/Orange.modelmaps.modelmap.rst
docs/rst/Orange.modelmaps.rst
docs/rst/conf.py
docs/rst/examples.mixwbcd.rst
docs/rst/examples.mixzoo.rst
docs/rst/examples.rfzoo.rst
docs/rst/index.rst
examples/__init__.py
examples/ensemble/__init__.py
examples/ensemble/rf_performance_build.py
examples/ensemble/rf_performance_plot_1.py
examples/ensemble/rf_performance_plot_2.py
examples/ensemble/rf_performance_plot_3.py
examples/ensemble/rfzoo.py
examples/modelmix/__init__.py
examples/modelmix/mixwbcd.py
examples/modelmix/mixzoo.py
orangecontrib/__init__.py
orangecontrib/modelmaps/__init__.py
orangecontrib/modelmaps/model.py
orangecontrib/modelmaps/modelmap.py
orangecontrib/modelmaps/widgets/OWModelEmbedder.py
orangecontrib/modelmaps/widgets/OWModelFile.py
orangecontrib/modelmaps/widgets/OWModelMap.py
orangecontrib/modelmaps/widgets/__init__.py
orangecontrib/modelmaps/widgets/icons/DistanceFile_16.png
orangecontrib/modelmaps/widgets/icons/DistanceFile_32.png
orangecontrib/modelmaps/widgets/icons/DistanceFile_40.png
orangecontrib/modelmaps/widgets/icons/DistanceFile_48.png
orangecontrib/modelmaps/widgets/icons/DistanceFile_60.png
orangecontrib/modelmaps/widgets/icons/Network_16.png
orangecontrib/modelmaps/widgets/icons/Network_32.png
orangecontrib/modelmaps/widgets/icons/Network_40.png
orangecontrib/modelmaps/widgets/icons/Network_48.png
orangecontrib/modelmaps/widgets/icons/Network_60.png
orangecontrib/modelmaps/widgets/icons/background_16.png
orangecontrib/modelmaps/widgets/icons/background_32.png
orangecontrib/modelmaps/widgets/icons/background_40.png
orangecontrib/modelmaps/widgets/icons/background_48.png
orangecontrib/modelmaps/widgets/icons/background_60.png
tests/__init__.py