Metadata-Version: 1.1
Name: Orange-ModelMaps
Version: 0.2.8
Summary: Orange Model Maps (space of prediction models) add-on for Orange data mining software package.
Home-page: http://orange.biolab.si/addons/
Author: Miha Stajdohar, University of Ljubljana, FRI
Author-email: miha.stajdohar@gmail.com
License: GPLv3
Download-URL: https://bitbucket.org/mstajdohar/orange-modelmaps/downloads
Keywords: data mining,machine learning,artificial intelligence,meta learning,orange,orange add-on
Platform: UNKNOWN
Classifier: Development Status :: 4 - Beta
Classifier: Environment :: X11 Applications :: Qt
Classifier: Environment :: Console
Classifier: Environment :: Plugins
Classifier: Programming Language :: Python
Classifier: License :: OSI Approved :: GNU General Public License v3 or later (GPLv3+)
Classifier: Operating System :: OS Independent
Classifier: Topic :: Scientific/Engineering :: Artificial Intelligence
Classifier: Topic :: Scientific/Engineering :: Visualization
Classifier: Topic :: Software Development :: Libraries :: Python Modules
Classifier: Intended Audience :: Education
Classifier: Intended Audience :: Science/Research
Classifier: Intended Audience :: Developers
